memuri/__init__.py
memuri/adapters/cache/redis.py
memuri/adapters/db/client.py
memuri/adapters/vectorstore/pgvector.py
memuri/adapters/vectorstore/redis_vector.py
memuri/core/__init__.py
memuri/core/categories.py
memuri/core/config.py
memuri/core/logging.py
memuri/core/telemetry.py
memuri/core/text_utils.py
memuri/domain/__init__.py
memuri/domain/interfaces.py
memuri/domain/models.py
memuri/factory.py
memuri/sdk/__init__.py
memuri/sdk/chat.py
memuri/sdk/client.py
memuri/services/__init__.py
memuri/services/classifier/__init__.py
memuri/services/classifier/keyword.py
memuri/services/classifier/ml.py
memuri/services/embedding.py
memuri/services/feedback.py
memuri/services/gating.py
memuri/services/llm.py
memuri/services/memory.py
memuri/services/rerank.py
memuri/services/retrieval.py
memuri/tests/README_TESTS.md
memuri/tests/__init__.py
memuri/tests/conftest.py
memuri/tests/run_latency_tests.py
memuri/tests/test_latency.py
memuri/tests/test_latency_benchmark.py
memuri/tests/test_memory_gating.py
memuri/workers/celery_app.py
memuri/workers/embed_tasks.py
memuri/workers/memory_tasks.py
memuri-0.1.6.dist-info/LICENSE
memuri-0.1.6.dist-info/METADATA
memuri-0.1.6.dist-info/WHEEL
memuri-0.1.6.dist-info/entry_points.txt
memuri-0.1.6.dist-info/RECORD
