Metadata-Version: 2.3
Name: memuri
Version: 0.1.6
Summary: Memuri is a self‑hosted memory infrastructure for AI applications, offering a unified, pluggable SDK to persist and retrieve conversational context with sub‑second latency. It enables any AI agent or assistant to remember key information across sessions—so your apps never forget what matters, while retaining full flexibility to swap storage backends, embedding models, and retrieval strategies.
License: MIT
Author: Ankhbayasgalan anhbaysgalan1@gmail.com
Requires-Python: >=3.10,<4.0
Classifier: Development Status :: 4 - Beta
Classifier: Intended Audience :: Developers
Classifier: License :: OSI Approved :: MIT License
Classifier: Programming Language :: Python :: 3
Classifier: Programming Language :: Python :: 3.10
Classifier: Programming Language :: Python :: 3.11
Classifier: Programming Language :: Python :: 3.12
Classifier: Programming Language :: Python :: 3.13
Classifier: Programming Language :: Python :: 3.8
Classifier: Programming Language :: Python :: 3.9
Classifier: Topic :: Scientific/Engineering :: Artificial Intelligence
Classifier: Topic :: Software Development :: Libraries :: Python Modules
Requires-Dist: aioredis (>=2.0.1,<3.0.0)
Requires-Dist: asyncpg (==0.30.0)
Requires-Dist: celery (==5.5.2)
Requires-Dist: faiss-cpu (==1.11.0)
Requires-Dist: google-genai (==1.16.1)
Requires-Dist: hnswlib (>=0.7.0,<0.8.0)
Requires-Dist: hydra-core (==1.3.2)
Requires-Dist: mkdocs (==1.6.1)
Requires-Dist: mkdocstrings (==0.29.1)
Requires-Dist: openai (==1.79.0)
Requires-Dist: opentelemetry-sdk (==1.33.1)
Requires-Dist: orjson (>=3.9.10,<4.0.0)
Requires-Dist: pgvector (==0.4.1)
Requires-Dist: prometheus-client (==0.22.0)
Requires-Dist: pydantic (==2.11.4)
Requires-Dist: pydantic-settings (>=2.1.0,<3.0.0)
Requires-Dist: pymilvus (>=2.3.3,<3.0.0)
Requires-Dist: qdrant-client (>=1.7.0,<2.0.0)
Requires-Dist: redis (==6.1.0)
Requires-Dist: sentence-transformers (>=2.2.2,<3.0.0)
Requires-Dist: sqlalchemy (==2.0.41)
Requires-Dist: uvloop (==0.21.0)
Project-URL: Repository, https://github.com/username/memuri
